agent_orchestra/__init__.py
agent_orchestra/py.typed
agent_orchestra/orchestrator/__init__.py
agent_orchestra/orchestrator/agent_pool.py
agent_orchestra/orchestrator/broker_config.py
agent_orchestra/orchestrator/call_broker.py
agent_orchestra/orchestrator/core.py
agent_orchestra/orchestrator/executors.py
agent_orchestra/orchestrator/executors_mcp.py
agent_orchestra/orchestrator/fs_utils.py
agent_orchestra/orchestrator/types.py
agent_orchestra/orchestrator/utils.py
agent_orchestra/sidecar/__init__.py
agent_orchestra/sidecar/client.pyi
agent_orchestra/sidecar/sidecar_adapter.py
agent_orchestra/sidecar/sidecar_agent.py
agent_orchestra/sidecar/sidecar_client.py
agent_orchestra/sidecar/sidecar_session.py
agent_orchestra/sidecar/stubs.pyi
agent_orchestra/sidecar/types.py
agentic_orchestra-0.1.0.dist-info/licenses/LICENSE
agentic_orchestra-0.1.0.dist-info/METADATA
agentic_orchestra-0.1.0.dist-info/WHEEL
agentic_orchestra-0.1.0.dist-info/top_level.txt
agentic_orchestra-0.1.0.dist-info/RECORD
