Metadata-Version: 2.4
Name: agentic-orchestra
Version: 0.1.0
Summary: The easiest way to create and orchestrate multi-agent fleets
Author: Agent Orchestra Contributors
License: MIT
Project-URL: Homepage, https://github.com/agent-orchestra/agent-orchestra
Project-URL: Repository, https://github.com/agent-orchestra/agent-orchestra
Project-URL: Issues, https://github.com/agent-orchestra/agent-orchestra/issues
Project-URL: Documentation, https://github.com/agent-orchestra/agent-orchestra/blob/main/README.md
Keywords: mcp,ai,agents,telemetry,policy,observability,orchestration
Classifier: Development Status :: 4 - Beta
Classifier: Intended Audience :: Developers
Classifier: License :: OSI Approved :: MIT License
Classifier: Programming Language :: Python :: 3
Classifier: Programming Language :: Python :: 3.8
Classifier: Programming Language :: Python :: 3.9
Classifier: Programming Language :: Python :: 3.10
Classifier: Programming Language :: Python :: 3.11
Classifier: Programming Language :: Python :: 3.12
Classifier: Topic :: Software Development :: Libraries :: Python Modules
Classifier: Topic :: System :: Monitoring
Requires-Python: >=3.11
License-File: LICENSE
Requires-Dist: mcp-use>=0.1.0
Requires-Dist: typing-extensions>=4.0.0
Requires-Dist: tenacity>=8.0.0
Provides-Extra: dev
Requires-Dist: pytest>=8; extra == "dev"
Requires-Dist: pytest-asyncio>=0.23; extra == "dev"
Requires-Dist: black>=22.0.0; extra == "dev"
Requires-Dist: isort>=5.0.0; extra == "dev"
Requires-Dist: mypy>=1.0.0; extra == "dev"
Dynamic: license-file
